dashai_plugin_hernan4/__init__.py
dashai_plugin_hernan4/dataloader_class_template.py
dashai_plugin_hernan4/metric_class_template.py
dashai_plugin_hernan4/model_class_template.py
dashai_plugin_hernan4/task_class_template.py
dashai_plugin_hernan4-1.0.dist-info/METADATA
dashai_plugin_hernan4-1.0.dist-info/WHEEL
dashai_plugin_hernan4-1.0.dist-info/entry_points.txt
dashai_plugin_hernan4-1.0.dist-info/RECORD
